ddkf/__init__.py
ddkf/ddkf.py
ddkf-4.1.0.dist-info/licenses/LICENSE
ddkf-4.1.0.dist-info/METADATA
ddkf-4.1.0.dist-info/WHEEL
ddkf-4.1.0.dist-info/top_level.txt
ddkf-4.1.0.dist-info/RECORD
