Metadata-Version: 2.4
Name: ddkf
Version: 4.1.0
Summary: Dual Dynamic Kernel Filtering (DDKF): A minimal package with arbitrary kernels and learnable parameters
Author-email: Skander Bensegueni <skander.bensegueni@example.com>, Yunis Kahalan <ykahalan@gmail.com>
License: MIT
Project-URL: Homepage, https://github.com/ykahalan/ddkf
Project-URL: Repository, https://github.com/ykahalan/ddkf
Project-URL: Documentation, https://github.com/ykahalan/ddkf/blob/main/README.md
Requires-Python: >=3.8
License-File: LICENSE
Requires-Dist: torch>=1.9
Requires-Dist: matplotlib>=3.4
Dynamic: license-file
